{"schemaVersion":"1.0","appDefinitionTemplate":{"id":"/providers/Microsoft.PowerApps/apps/","type":"Microsoft.PowerApps/apps","tags":{"primaryDeviceWidth":"1366","primaryDeviceHeight":"768","supportsPortrait":"true","supportsLandscape":"true","primaryFormFactor":"Tablet","showStatusBar":"false","publisherVersion":"3.24041.27","minimumRequiredApiVersion":"2.2.0","hasComponent":"true","hasUnlockedComponent":"true","isUnifiedRootApp":"false","offlineLargeFilesSupport":"false","sienaVersion":"20240417T103427Z-3.24041.27.0"},"properties":{"appVersion":"2024-04-17T10:34:27Z","lifeCycleId":"Published","createdByClientVersion":{"major":3,"minor":24041,"build":27,"revision":0,"majorRevision":0,"minorRevision":0},"minClientVersion":{"major":3,"minor":24041,"build":27,"revision":0,"majorRevision":0,"minorRevision":0},"backgroundColor":"RGBA(0,176,240,1)","backgroundImageUri":"/14629869059232713691/N8cdd4432-a424-4504-84b2-3c530c9878e3-logoSmallFile","displayName":"Teste_Tablet","description":"","commitMessage":"","appUris":{"documentUri":{"value":"/14629869059232713691/Nfd14c104-c8f5-4f55-8eb8-bb3863ceebd6-document.msapp"},"imageUris":[],"additionalUris":[{"isSolutionAware":false,"value":"/14629869059232713691/Nb5781edc-3ed9-4247-a9a7-0259e7ef1cc3-identity.json"}]},"createdTime":"0001-01-01T00:00:00Z","lastModifiedTime":"0001-01-01T00:00:00Z","sharedGroupsCount":0,"sharedUsersCount":0,"connectionReferences":{},"authorizationReferences":[{"resourceId":"powerbi"}],"databaseReferences":{"default.cds":{"databaseDetails":{"referenceType":"Environmental","environmentName":"default.cds","overrideValues":{"status":"NotSpecified","environmentVariableName":""}},"dataSources":{"PhoneTablet":{"entitySetName":"cr9f8_phonetablets","logicalName":"cr9f8_phonetablet","isHidden":false},"GymMaintenance":{"entitySetName":"cr9f8_gymmaintenancelogs","logicalName":"cr9f8_gymmaintenancelog","isHidden":false},"TabelaFotosVerificar":{"entitySetName":"cr9f8_tabelafotosverificars","logicalName":"cr9f8_tabelafotosverificar","isHidden":false},"TabelaFotos":{"entitySetName":"cr9f8_tabelafotoses","logicalName":"cr9f8_tabelafotos","isHidden":false}},"actions":["providers/PowerPlatform.Governance/Operations/Read","providers/PowerPlatform.Governance/Operations/Write","providers/PowerPlatform.Governance/Operations/Delete"]}},"almMode":"Environment","performanceOptimizationEnabled":true,"canConsumeAppPass":true,"enableModernRuntimeMode":false,"executionRestrictions":{"isTeamsOnly":false,"dataLossPreventionEvaluationResult":{"status":"Compliant","lastEvaluationDate":"2024-03-13T16:04:27.4053515Z","violations":[],"violationsByPolicy":[],"violationErrorMessage":"A aplicação utiliza os seguintes conectores: ."}}},"appType":"ClassicCanvasApp","appComponents":[]}}